{
  "error": false,
  "id": "0eb08a60604e55c23ab7c13be473fe588286d305cdfad80a6f2cfa3374128f08",
  "filename": "TenX-OS-v3.1_RMX1851-11.0-20210517-1919-Flash-Official.zip",
  "datetime":1621278810,
  "version": "v3.0",
  "size":1542079224,
  "url": "https://sourceforge.net/projects/tenx-os/files/RMX1851/TenX-OS-v3.1_RMX1851-11.0-20210517-1919-Flash-Official.zip/download",
  "filehash": "620b47605152a84a7aeb0c8ba74a26c7",
  "website_url": "",
  "news_url": "https://t.me/TenX_Updates",
  "donate_url": "",
  "maintainer": "Supratim Dey",
  "maintainer_url": "https://t.me/supratimdey",
  "forum_url": ""
}
